issmoex/__init__.py
issmoex/issmoex.py
test/__init__.py
test/test.py
ISSMOEX-1.1.6.dist-info/LICENSE
ISSMOEX-1.1.6.dist-info/METADATA
ISSMOEX-1.1.6.dist-info/WHEEL
ISSMOEX-1.1.6.dist-info/top_level.txt
ISSMOEX-1.1.6.dist-info/RECORD
