Metadata-Version: 2.1
Name: ISSMOEX
Version: 1.1.6
Summary: A package to interact with the MOEX ISS API
Home-page: https://github.com/alexandrettto/issmoex
Author: Illyuk Alexander
Author-email: aaillyuk@gmail.com
License: MIT
Classifier: Programming Language :: Python :: 3
Classifier: License :: OSI Approved :: MIT License
Classifier: Operating System :: OS Independent
License-File: LICENSE
Requires-Dist: asyncio
Requires-Dist: aiohttp
Requires-Dist: pandas
Requires-Dist: nest-asyncio
Requires-Dist: tqdm
